safe_rcm/__init__.py
safe_rcm/api.py
safe_rcm/calibrations.py
safe_rcm/manifest.py
safe_rcm/xml.py
safe_rcm/product/dicttoolz.py
safe_rcm/product/predicates.py
safe_rcm/product/reader.py
safe_rcm/product/transformers.py
safe_rcm/product/utils.py
safe_rcm/tests/test_product_utils.py
safe_rcm/tests/test_xml.py
xarray_safe_rcm-2026.1.0.dist-info/licenses/LICENSE
xarray_safe_rcm-2026.1.0.dist-info/METADATA
xarray_safe_rcm-2026.1.0.dist-info/WHEEL
xarray_safe_rcm-2026.1.0.dist-info/top_level.txt
xarray_safe_rcm-2026.1.0.dist-info/RECORD
