Metadata-Version: 2.4
Name: xarray-safe-rcm
Version: 2026.1.0
Summary: xarray reader for radarsat constellation mission (RCM) SAFE files
License: MIT
Requires-Python: >=3.10
License-File: LICENSE
Requires-Dist: toolz
Requires-Dist: numpy
Requires-Dist: xarray
Requires-Dist: lxml
Requires-Dist: xmlschema
Requires-Dist: rioxarray
Requires-Dist: fsspec
Requires-Dist: pandas
Requires-Dist: exceptiongroup; python_version < "3.11"
Dynamic: license-file
